mnultitool/__init__.py
mnultitool/interpolate/__init__.py
mnultitool/interpolate/spline.py
mnultitool/interpolate/utils.py
mnultitool/matrix/__init__.py
mnultitool/matrix/classification.py
mnultitool/matrix/matrix.py
mnultitool/misc/__init__.py
mnultitool/misc/approximate.py
mnultitool/misc/norm.py
mnultitool/misc/rigid.py
mnultitool/misc/utils.py
mnultitool/plot/__init__.py
mnultitool/plot/plot.py
mnultitool-1.0.6.dist-info/DESCRIPTION.rst
mnultitool-1.0.6.dist-info/METADATA
mnultitool-1.0.6.dist-info/RECORD
mnultitool-1.0.6.dist-info/WHEEL
mnultitool-1.0.6.dist-info/metadata.json
mnultitool-1.0.6.dist-info/top_level.txt
