Metadata-Version: 2.0
Name: mnultitool
Version: 1.0.6
Summary: A multitool for Numerical Methods
Home-page: https://github.com/artus9033/MNultitool
Author: artus9033
Author-email: artus9033@gmail.com
License: UNKNOWN
Keywords: numerical,math,interpolation
Platform: UNKNOWN
Classifier: Development Status :: 4 - Beta
Classifier: Intended Audience :: Developers
Classifier: Programming Language :: Python :: 3
Classifier: Programming Language :: Python :: 3.6
Classifier: Programming Language :: Python :: 3.7
Classifier: Programming Language :: Python :: 3.8
Classifier: Programming Language :: Python :: 3.9
Classifier: Programming Language :: Python :: 3 :: Only
Requires-Python: >=3.6, <4
